{
  "_fv": 43,
  "_type": "gui",
  "definition": {
    "type": 0,
    "width": 190,
    "height": 200,
    "inventoryOffsetX": 0,
    "inventoryOffsetY": 0,
    "renderBgLayer": true,
    "doesPauseGame": false,
    "components": [
      {
        "type": "label",
        "data": {
          "name": "label_adminshop_plant_section",
          "text": {
            "fixedValue": "Adminshop - fast action "
          },
          "color": {
            "value": -52480,
            "falpha": 0.0
          },
          "x": 142,
          "y": 21
        }
      },
      {
        "type": "button",
        "data": {
          "name": "button_honey_comb",
          "text": "Diamond pickaxe",
          "onClick": {
            "name": "Connectadminshoputilitiesdiampic"
          },
          "width": 81,
          "height": 20,
          "x": 217,
          "y": 94
        }
      },
      {
        "type": "button",
        "data": {
          "name": "button_leather",
          "text": "Netherrack",
          "onClick": {
            "name": "Connectadhblknetherrack"
          },
          "width": 61,
          "height": 20,
          "x": 130,
          "y": 188
        }
      },
      {
        "type": "button",
        "data": {
          "name": "button_feather",
          "text": "Redstone",
          "onClick": {
            "name": "Connectadminshoputilitiesredstone"
          },
          "width": 61,
          "height": 20,
          "x": 237,
          "y": 71
        }
      },
      {
        "type": "button",
        "data": {
          "name": "button_ink_sac",
          "text": "Coal",
          "onClick": {
            "name": "Connectadhorecoal"
          },
          "width": 43,
          "height": 20,
          "x": 255,
          "y": 116
        }
      },
      {
        "type": "button",
        "data": {
          "name": "button_glow_in_sac",
          "text": "Oak wood",
          "onClick": {
            "name": "Connectadhblkoakwood"
          },
          "width": 82,
          "height": 20,
          "x": 130,
          "y": 95
        }
      },
      {
        "type": "button",
        "data": {
          "name": "button_blaze",
          "text": "Bone",
          "onClick": {
            "name": "Connectadminshopmobsbone"
          },
          "width": 51,
          "height": 20,
          "x": 130,
          "y": 71
        }
      },
      {
        "type": "button",
        "data": {
          "name": "button_gun_powder",
          "text": "Ender pearl",
          "onClick": {
            "name": "Connectadminshopmobsenderpearl"
          },
          "width": 77,
          "height": 20,
          "x": 221,
          "y": 46
        }
      },
      {
        "type": "button",
        "data": {
          "name": "button_steak",
          "text": "Steak",
          "onClick": {
            "name": "ConnectAdminshopmobs2steak"
          },
          "width": 51,
          "height": 20,
          "x": 130,
          "y": 46
        }
      },
      {
        "type": "label",
        "data": {
          "name": "label_wip",
          "text": {
            "fixedValue": "Useful"
          },
          "color": {
            "value": -1,
            "falpha": 0.0
          },
          "x": 195,
          "y": 31
        }
      },
      {
        "type": "label",
        "data": {
          "name": "label_fast_sell",
          "text": {
            "fixedValue": "Fast sell"
          },
          "color": {
            "value": -3407872,
            "falpha": 0.0
          },
          "x": 193,
          "y": 176
        }
      },
      {
        "type": "button",
        "data": {
          "name": "button_stone",
          "text": "Cobblestone",
          "onClick": {
            "name": "Connectadhblkstone"
          },
          "width": 68,
          "height": 20,
          "x": 230,
          "y": 189
        }
      },
      {
        "type": "button",
        "data": {
          "name": "button_emeraude",
          "text": "Emerald",
          "onClick": {
            "name": "Connectadminshoputilitiesemerald"
          },
          "width": 67,
          "height": 20,
          "x": 129,
          "y": 117
        }
      },
      {
        "type": "image",
        "data": {
          "image": "right_gray_line.png",
          "use1Xscale": false,
          "x": 208,
          "y": 18
        }
      },
      {
        "type": "image",
        "data": {
          "image": "left_gray_line.png",
          "use1Xscale": false,
          "x": 118,
          "y": 18
        }
      },
      {
        "type": "imagebutton",
        "data": {
          "name": "imagebutton_arrow_adminshop",
          "image": "arrow_adminshop.png",
          "hoveredImage": "arrow_adminshop_poi.png",
          "onClick": {
            "name": "Adminshop_open"
          },
          "x": 123,
          "y": 22
        }
      },
      {
        "type": "imagebutton",
        "data": {
          "name": "imagebutton_cross_no_button",
          "image": "cross_no_button.png",
          "hoveredImage": "pointed_cross_no_button.png",
          "onClick": {
            "name": "Closegui"
          },
          "x": 281,
          "y": 23
        }
      }
    ],
    "gridSettings": {
      "sx": 18,
      "sy": 18,
      "ox": 11,
      "oy": 15,
      "snapOnGrid": false
    }
  }
}